yappy/__init__.py
yappy/__version__.py
yappy/main.py
yappy/py.typed
yappy/types.py
yappy-0.0.2.dist-info/LICENSE
yappy-0.0.2.dist-info/METADATA
yappy-0.0.2.dist-info/WHEEL
yappy-0.0.2.dist-info/top_level.txt
yappy-0.0.2.dist-info/RECORD
