Metadata-Version: 2.1
Name: yappy
Version: 0.0.2
Summary: Yet another way to turn your pydantic model into console application.
Home-page: https://github.com/silversum/yappy
Author: Artem Zakhov
Author-email: solutio.sciurus@gmail.com
License: UNKNOWN
Platform: UNKNOWN
Classifier: Development Status :: 4 - Beta
Classifier: License :: OSI Approved :: MIT License
Classifier: Programming Language :: Python :: 3 :: Only
Classifier: Programming Language :: Python :: 3
Classifier: Programming Language :: Python :: 3.9
Classifier: Typing :: Typed
Requires-Python: ~=3.9.0
License-File: LICENSE
Requires-Dist: pydantic (~=1.8.2)
Requires-Dist: click (~=8.0.3)
